pycax/CITATION
pycax/MANIFEST.in
pycax/__init__.py
pycax/_version.py
pycax/caxutils.py
pycax/data/xport_colnames_json.txt
pycax/datasets/__init__.py
pycax/datasets/datasets.py
pycax/datasets/test_datasets.py
pycax/hli/__init__.py
pycax/hli/hli.py
pycax/hli/test_hli.py
pycax/tables/__init__.py
pycax/tables/tables.py
pycax/tables/test_tables.py
pycax_client-1.0.3.dist-info/LICENSE
pycax_client-1.0.3.dist-info/METADATA
pycax_client-1.0.3.dist-info/WHEEL
pycax_client-1.0.3.dist-info/top_level.txt
pycax_client-1.0.3.dist-info/RECORD
