Metadata-Version: 2.1
Name: pycax-client
Version: 1.0.3
Summary: Python client for CAX
Home-page: https://github.com/nwfsc-math-bio/pycax
Author: Eli Holmes and Mari Williams
Author-email: eli.holmes@noaa.gov
License: MIT
Project-URL: Documentation, https://nwfsc-math-bio.github.io/pycax
Project-URL: Bug Tracker, https://github.com/nwfsc-math-bio/pycax/issues
Project-URL: Source Code, https://github.com/nwfsc-math-bio/pycax
Classifier: Development Status :: 2 - Pre-Alpha
Classifier: Intended Audience :: Science/Research
Classifier: License :: OSI Approved :: MIT License
Classifier: Operating System :: OS Independent
Classifier: Natural Language :: English
Classifier: Programming Language :: Python :: 3
Classifier: Topic :: Scientific/Engineering :: Bio-Informatics
Requires-Python: >=3.7
License-File: LICENSE
Requires-Dist: requests (>2.7)
Requires-Dist: pandas
